qrcodecreator.py
qrcodecreator-1.0.0.dist-info/WHEEL
qrcodecreator-1.0.0.dist-info/METADATA
qrcodecreator-1.0.0.dist-info/RECORD
